Workbook

Sheet Executive Summary
B2: SKYFINSERV FINANCIAL SERVICES — CREDIT APPRAISAL MEMORANDUM
B3: Case: Padia Imaging / Govind Padiya | Debt Consolidation, Balance Transfer & Top-Up Evaluation
B5: Total Existing POS | C5: BT Takeover POS | D5: Property Collateral Eligibility | E5: Top-Up / In-Hand Surplus | F5: Monthly EMI Reduction
B6: 68001823 | C6: 38937424 | D6: 44360750 | E6: 6062576 | F6: 391984
B8: 1. BALANCE TRANSFER & RESTRUCTURING PROPOSAL SUMMARY
B9: Parameter / Metric | C9: Existing Position | D9: Proposed Restructured Terms | E9: Net Advantage / Savings | F9: Strategic Notes
B10: Total Loan Facilities Count | C10: 8 | D10: 1 | E10: 7 Loans Consolidated | F10: Reduces administrative burden
B11: Total Active Outstanding (POS) | C11: 68001823 | D11: 45000000 | E11: 23001823 | F11: BOI CGTMSE retained; 7 high-cost loans cleared
B12: Balance Transfer Takeover Amount | C12: 38937424 | D12: 38937424 | E12: Full Takeover of 7 Loans | F12: HDFC, ICICI, Bajaj, LIC, HDB, L&T, BOI Ed.
B13: Top-Up / Liquidity Surplus | C13: 0 | D13: 6062576 | E13: ₹ 60,62,576 In-Hand Cash | F13: Working capital infusion for business
B14: Monthly EMI Outgo (BT Facilities) | C14: 835234 | D14: 443250 | E14: 391984 | F14: 46.9% Monthly Cashflow Savings (₹3.92L/mo)
B15: Effective Interest Rate (Blended ROI) | C15: 0.1085 | D15: 0.0815 | E15: 0.027 | F15: ROI reduction of 270 bps (from 10.85% to 8.15%)
B16: Proposed Loan Tenure | C16: 27 - 80 Months | D16: 180 Months (15 Yrs) | E16: Extended amortisation | F16: Reduces debt service burden drastically
B17: Total Foreclosure & Switching Cost | C17: 0 | D17: 1309451 | E17: FC (₹10.32L) + PF & Stamp (₹2.77L) | F17: Factored into overall deal structure
B18: Projected Net Financial Savings | C18: 0 | D18: 3549251 | E18: ₹ 35,49,251 Net Savings | F18: Net interest saved over existing tenures
B20: 2. PROPERTY COLLATERAL & LTV VALUATION SUMMARY
B21: Property Identification | C21: Plot Area (sq.ft) | D21: Land Rate (₹/sqft) | E21: Construction (sq.ft) | F21: Market Value (₹) | G21: LTV % | H21: Eligible Loan (₹)
B22: Property 1 (Govind Padiya) | C22: 1830 | D22: 12000 | E22: 1565 | F22: 25872500 | G22: 0.7 | H22: 18110750
B23: Property 2 (Govind Padiya) | C23: 1500 | D23: 25000 | E23: 0 | F23: 37500000 | G23: 0.7 | H23: 26250000
B24: Total Assessed Collateral | F24: =SUM(F22:F23) -> 63372500 | H24: =SUM(H22:H23) -> 44360750

Sheet Existing Loans
A1: EXISTING LOAN OBLIGATIONS & BALANCE TRANSFER (BT) MATRIX
A2: Client: Padia Imaging / Govind Padiya | Live Portfolio Assessment & Takeover Identification
A4: Sr | B4: Loan Belongs To | C4: Bank / Provider | D4: Facility Type | E4: Sanction Amount (₹) | F4: Tenure (M) | G4: Start Date | H4: EMIs Paid | I4: Monthly EMI (₹) | J4: Outstanding POS (₹) | K4: Obligation | L4: EMI Obligation (₹) | M4: Take Over | N4: BT EMI (₹) | O4: BT Amount (₹)
A5: 1 | B5: Padia Imaging | C5: HDFC | D5: EQUIPMENT | E5: 13257000 | F5: 90 | G5: 44695.771 | H5: 45 | I5: 208282 | J5: 5567405 | K5: No | L5: =IF(UPPER(K5)="YES",I5,0) -> 0 | M5: Yes | N5: =IF(UPPER(M5)="YES",I5,0) -> 208282 | O5: =IF(UPPER(M5)="YES",J5,0) -> 5567405
A6: 2 | B6: Padia Imaging | C6: Bank of India | D6: CGTMSE | E6: 32700000 | F6: — | G6: 45405.771 | H6: — | I6: 500000 | J6: 29064399 | K6: No | L6: =IF(UPPER(K6)="YES",I6,0) -> 0 | M6: No | N6: =IF(UPPER(M6)="YES",I6,0) -> 0 | O6: =IF(UPPER(M6)="YES",J6,0) -> 0
A7: 3 | B7: Govind Padiya | C7: ICICI Bank | D7: BL | E7: 6000000 | F7: 60 | G7: 45050.771 | H7: 33 | I7: 128702 | J7: 3189332 | K7: No | L7: =IF(UPPER(K7)="YES",I7,0) -> 0 | M7: Yes | N7: =IF(UPPER(M7)="YES",I7,0) -> 128702 | O7: =IF(UPPER(M7)="YES",J7,0) -> 3189332
A8: 4 | B8: Govind Padiya | C8: Bajaj | D8: Flexy OD | E8: 6081559 | F8: 96 | G8: 45566.771 | H8: 27 | I8: 69685 | J8: 6081559 | K8: No | L8: =IF(UPPER(K8)="YES",I8,0) -> 0 | M8: Yes | N8: =IF(UPPER(M8)="YES",I8,0) -> 69685 | O8: =IF(UPPER(M8)="YES",J8,0) -> 6081559
A9: 5 | B9: Govind Padiya | C9: LIC | D9: HL | E9: 7900000 | F9: 133 | G9: 44330.771 | H9: 57 | I9: 90716 | J9: 5194122 | K9: No | L9: =IF(UPPER(K9)="YES",I9,0) -> 0 | M9: Yes | N9: =IF(UPPER(M9)="YES",I9,0) -> 90716 | O9: =IF(UPPER(M9)="YES",J9,0) -> 5194122
A10: 6 | B10: Govind Padiya | C10: HDB | D10: LAP | E10: 17800000 | F10: 108 | G10: 45165.771 | H10: 28 | I10: 245809 | J10: 14524298 | K10: No | L10: =IF(UPPER(K10)="YES",I10,0) -> 0 | M10: Yes | N10: =IF(UPPER(M10)="YES",I10,0) -> 245809 | O10: =IF(UPPER(M10)="YES",J10,0) -> 14524298
A11: 7 | B11: Govind Padiya | C11: LNT | D11: Drop Line OD | E11: 2000000 | F11: — | G11: 45835.771 | H11: — | I11: 67040 | J11: 1720065 | K11: No | L11: =IF(UPPER(K11)="YES",I11,0) -> 0 | M11: Yes | N11: =IF(UPPER(M11)="YES",I11,0) -> 67040 | O11: =IF(UPPER(M11)="YES",J11,0) -> 1720065
A12: 8 | B12: Govind Padiya (Rohan) | C12: BOI | D12: Education Loan | E12: 2500000 | F12: — | G12: 45543.771 | H12: — | I12: 25000 | J12: 2660643 | K12: No | L12: =IF(UPPER(K12)="YES",I12,0) -> 0 | M12: Yes | N12: =IF(UPPER(M12)="YES",I12,0) -> 25000 | O12: =IF(UPPER(M12)="YES",J12,0) -> 2660643
A13: Total | E13: =SUM(E5:E12) -> 88238559 | I13: =SUM(I5:I12) -> 1335234 | J13: =SUM(J5:J12) -> 68001823 | L13: =SUM(L5:L12) -> 0 | N13: =SUM(N5:N12) -> 835234 | O13: =SUM(O5:O12) -> 38937424

Sheet Collateral & LTV
A1: PROPERTY COLLATERAL VALUATION & LTV LOAN ELIGIBILITY MATRIX
A3: Sr | B3: Property Description / Title | C3: Land Area (sq.ft) | D3: Land Rate (₹/sqft) | E3: Land Value (₹) | F3: Built-Up Area (sq.ft) | G3: Const. Rate (₹/sqft) | H3: Const. Value (₹) | I3: Total Market Value (₹) | J3: LTV Cap % | K3: Eligible Loan Amount (₹)
A4: 1 | B4: Property 1 — Govind Padiya (Plot + Construction) | C4: 1830 | D4: 12000 | E4: =C4*D4 -> 21960000 | F4: 1565 | G4: 2500 | H4: =F4*G4 -> 3912500 | I4: =E4+H4 -> 25872500 | J4: 0.7 | K4: =I4*J4 -> 18110750
A5: 2 | B5: Property 2 — Govind Padiya (Prime Commercial Plot) | C5: 1500 | D5: 25000 | E5: =C5*D5 -> 37500000 | F5: 0 | G5: 0 | H5: =F5*G5 -> 0 | I5: =E5+H5 -> 37500000 | J5: 0.7 | K5: =I5*J5 -> 26250000
B6: Total Collateral Valuation & Loan Limit | E6: =SUM(E4:E5) -> 59460000 | H6: =SUM(H4:H5) -> 3912500 | I6: =SUM(I4:I5) -> 63372500 | K6: =SUM(K4:K5) -> 44360750

Sheet BT Benefit Analysis
A1: BALANCE TRANSFER (BT) COST-BENEFIT & INTEREST SAVINGS ANALYSIS
A2: Detailed facility-wise comparison factoring Foreclosure (FC) Charges and Processing Fees + Stamp Duty
A4: Lender | B4: Principal POS (₹) | C4: Existing ROI | D4: Existing EMI (₹) | E4: Tenure (M) | F4: Existing Total Outgo (₹) | G4: Existing Total Interest (₹) | H4: FC % | I4: Foreclosure Charges (₹) | J4: Offered ROI | K4: Offered EMI (₹) | L4: Offered Total Outgo (₹) | M4: Offered Total Interest (₹) | N4: PF+Stamp % | O4: PF & Stamp Duty (₹) | P4: Net Customer Benefit (₹)
A5: HDFC | B5: 5567405 | C5: 0.103 | D5: 208282 | E5: 45 | F5: =D5*E5 -> 9372690 | G5: =F5-B5 -> 3805285 | H5: 0.025 | I5: =B5*H5 -> 139185 | J5: 0.081 | K5: 143874 | L5: =K5*E5 -> 6474330 | M5: =L5-B5 -> 906925 | N5: 0.008 | O5: =B5*N5 -> 44539 | P5: =G5-I5-M5-O5
A6: ICICI Bank | B6: 3189332 | C6: 0.105 | D6: 128702 | E6: 27 | F6: =D6*E6 -> 3474954 | G6: =F6-B6 -> 285622 | H6: 0 | I6: =B6*H6 -> 0 | J6: 0.081 | K6: 129612 | L6: =K6*E6 -> 3499524 | M6: =L6-B6 -> 310192 | N6: 0.008 | O6: =B6*N6 -> 25515 | P6: =G6-I6-M6-O6
A7: Bajaj | B7: 6081559 | C7: 0.1375 | D7: 140721 | E7: 60 | F7: =D7*E7 -> 8443260 | G7: =F7-B7 -> 2361701 | H7: 0.04 | I7: =B7*H7 -> 243262 | J7: 0.085 | K7: 124773 | L7: =K7*E7 -> 7486380 | M7: =L7-B7 -> 1404821 | N7: 0.008 | O7: =B7*N7 -> 48652 | P7: =G7-I7-M7-O7
A8: LIC | B8: 5194122 | C8: 0.092 | D8: 90716 | E8: 76 | F8: =D8*E8 -> 6894416 | G8: =F8-B8 -> 1700294 | H8: 0 | I8: =B8*H8 -> 0 | J8: 0.076 | K8: 86319 | L8: =K8*E8 -> 6560244 | M8: =L8-B8 -> 1366122 | N8: 0.0055 | O8: =B8*N8 -> 28568 | P8: =G8-I8-M8-O8
A9: HDB | B9: 14524298 | C9: 0.094 | D9: 245809 | E9: 80 | F9: =D9*E9 -> 19664720 | G9: =F9-B9 -> 5140422 | H9: 0.04 | I9: =B9*H9 -> 580972 | J9: 0.085 | K9: 238452 | L9: =K9*E9 -> 19076160 | M9: =L9-B9 -> 4551862 | N9: 0.008 | O9: =B9*N9 -> 116194 | P9: =G9-I9-M9-O9
A10: LNT | B10: 1720065 | C10: 0.125 | D10: 67040 | E10: 30 | F10: =D10*E10 -> 2011200 | G10: =F10-B10 -> 291135 | H10: 0.04 | I10: =B10*H10 -> 68803 | J10: 0.081 | K10: 63530 | L10: =K10*E10 -> 1905900 | M10: =L10-B10 -> 185835 | N10: 0.008 | O10: =B10*N10 -> 13761 | P10: =G10-I10-M10-O10
A11: BOI (Edu) | B11: 2660643 | C11: 0.09 | D11: 25000 | E11: 106 | F11: =D11*E11 -> 2650000 | G11: =F11-B11 -> -10643 | H11: 0 | I11: =B11*H11 -> 0 | J11: 0.085 | K11: 24500 | L11: =K11*E11 -> 2597000 | M11: =L11-B11 -> -63643 | N11: 0.005 | O11: =B11*N11 -> 13303 | P11: =G11-I11-M11-O11
A12: Total | B12: =SUM(B5:B11) -> 38937424 | D12: =SUM(D5:D11) -> 906270 | F12: =SUM(F5:F11) -> 52520858 | G12: =SUM(G5:G11) -> 13583434 | I12: =SUM(I5:I11) -> 1032222 | K12: =SUM(K5:K11) -> 810969 | L12: =SUM(L5:L11) -> 47600746 | M12: =SUM(M5:M11) -> 8663322 | O12: =SUM(O5:O11) -> 290532 | P12: =SUM(P5:P11) -> 3597358

Sheet 14M Horizon Comparison
A1: SHORT-TERM 14-MONTH HORIZON CASH-FLOW & SWITCHING EXPENSES COMPARISON
A2: Comparing immediate 14-month cashflow reduction against switching costs (Foreclosure + Processing Fees)
A4: Lender | B4: Existing ROI | C4: Existing EMI (₹) | D4: Horizon (M) | E4: Existing Total Pay (₹) | F4: Offered ROI | G4: Offered EMI (₹) | H4: Horizon (M) | I4: Offered Total Pay (₹) | J4: Gross Savings (₹) | K4: FC % | L4: Foreclosure (₹) | M4: PF+Stamp % | N4: PF & Stamp (₹) | O4: Total Expenses (₹)
A5: HDFC | B5: 0.103 | C5: 208282 | D5: 14 | E5: =C5*D5 -> 2915948 | F5: 0.081 | G5: 143874 | H5: 14 | I5: =G5*H5 -> 2014236 | J5: =E5-I5 -> 901712 | K5: 0.025 | L5: ='BT Benefit Analysis'!I5 | M5: 0.008 | N5: ='BT Benefit Analysis'!O5 | O5: =L5+N5
A6: ICICI Bank | B6: 0.105 | C6: 128702 | D6: 14 | E6: =C6*D6 -> 1801828 | F6: 0.081 | G6: 129612 | H6: 14 | I6: =G6*H6 -> 1814568 | J6: =E6-I6 -> -12740 | K6: 0 | L6: ='BT Benefit Analysis'!I6 | M6: 0.008 | N6: ='BT Benefit Analysis'!O6 | O6: =L6+N6
A7: Bajaj | B7: 0.1375 | C7: 140721 | D7: 14 | E7: =C7*D7 -> 1970094 | F7: 0.085 | G7: 124773 | H7: 14 | I7: =G7*H7 -> 1746822 | J7: =E7-I7 -> 223272 | K7: 0.04 | L7: ='BT Benefit Analysis'!I7 | M7: 0.008 | N7: ='BT Benefit Analysis'!O7 | O7: =L7+N7
A8: LIC | B8: 0.092 | C8: 90716 | D8: 14 | E8: =C8*D8 -> 1270024 | F8: 0.076 | G8: 86319 | H8: 14 | I8: =G8*H8 -> 1208466 | J8: =E8-I8 -> 61558 | K8: 0 | L8: ='BT Benefit Analysis'!I8 | M8: 0.0055 | N8: ='BT Benefit Analysis'!O8 | O8: =L8+N8
A9: HDB | B9: 0.094 | C9: 245809 | D9: 14 | E9: =C9*D9 -> 3441326 | F9: 0.085 | G9: 238452 | H9: 14 | I9: =G9*H9 -> 3338328 | J9: =E9-I9 -> 102998 | K9: 0.04 | L9: ='BT Benefit Analysis'!I9 | M9: 0.008 | N9: ='BT Benefit Analysis'!O9 | O9: =L9+N9
A10: LNT | B10: 0.125 | C10: 67040 | D10: 14 | E10: =C10*D10 -> 938560 | F10: 0.081 | G10: 63530 | H10: 14 | I10: =G10*H10 -> 889420 | J10: =E10-I10 -> 49140 | K10: 0.04 | L10: ='BT Benefit Analysis'!I10 | M10: 0.008 | N10: ='BT Benefit Analysis'!O10 | O10: =L10+N10
A11: Total | E11: =SUM(E5:E10) -> 12337780 | I11: =SUM(I5:I10) -> 11011840 | J11: =SUM(J5:J10) -> 1325940 | L11: =SUM(L5:L10) -> 1032222 | N11: =SUM(N5:N10) -> 277229 | O11: =SUM(O5:O10) -> 1309451

Sheet Working Model (All-In-One)
A1: SKYFINSERV CONSOLIDATED CREDIT WORKING MODEL
A3: Loan Belongs To | B3: Loan Provider | C3: Type | D3: Sanction Amount (₹) | E3: EMI / Interest (₹) | F3: Outstanding Amount (₹) | G3: Obligation | H3: EMI Obligation (₹) | I3: Take Over | J3: BT EMI (₹) | K3: BT Amount (₹) | M3: Area (sq.ft) | N3: Rate (₹) | O3: Construction (sq.ft) | P3: Rate (₹) | Q3: Total Value (₹) | R3: LTV | S3: Eligible Amount (₹)
A4: Padia Imaging | B4: HDFC | C4: EQUIPMENT | D4: 13257000 | E4: 208282 | F4: 5567405 | G4: No | H4: =IF(UPPER(G4)="YES",E4,0) | I4: Yes | J4: =IF(UPPER(I4)="YES",E4,0) | K4: =IF(UPPER(I4)="YES",F4,0) | M4: 1830 | N4: 12000 | O4: 1565 | P4: 2500 | Q4: =(M4*N4)+(O4*P4) | R4: 0.7 | S4: =Q4*R4
A5: Padia Imaging | B5: Bank of India | C5: CGTMSE | D5: 32700000 | E5: 500000 | F5: 29064399 | G5: No | H5: =IF(UPPER(G5)="YES",E5,0) | I5: No | J5: =IF(UPPER(I5)="YES",E5,0) | K5: =IF(UPPER(I5)="YES",F5,0) | M5: 1500 | N5: 25000 | O5: 0 | P5: 0 | Q5: =(M5*N5)+(O5*P5) | R5: 0.7 | S5: =Q5*R5
A6: Govind Padiya | B6: ICICI Bank | C6: BL | D6: 6000000 | E6: 128702 | F6: 3189332 | G6: No | H6: =IF(UPPER(G6)="YES",E6,0) | I6: Yes | J6: =IF(UPPER(I6)="YES",E6,0) | K6: =IF(UPPER(I6)="YES",F6,0) | M6: Total Property | Q6: =SUM(Q4:Q5) | S6: =SUM(S4:S5)
A7: Govind Padiya | B7: Bajaj | C7: Flexy OD | D7: 6081559 | E7: 69685 | F7: 6081559 | G7: No | H7: =IF(UPPER(G7)="YES",E7,0) | I7: Yes | J7: =IF(UPPER(I7)="YES",E7,0) | K7: =IF(UPPER(I7)="YES",F7,0)
A8: Govind Padiya | B8: LIC | C8: HL | D8: 7900000 | E8: 90716 | F8: 5194122 | G8: No | H8: =IF(UPPER(G8)="YES",E8,0) | I8: Yes | J8: =IF(UPPER(I8)="YES",E8,0) | K8: =IF(UPPER(I8)="YES",F8,0) | M8: Comparison | N8: Eligibility Limit | O8: Take Over (POS) | P8: Surplus / In-Hand
A9: Govind Padiya | B9: HDB | C9: LAP | D9: 17800000 | E9: 245809 | F9: 14524298 | G9: No | H9: =IF(UPPER(G9)="YES",E9,0) | I9: Yes | J9: =IF(UPPER(I9)="YES",E9,0) | K9: =IF(UPPER(I9)="YES",F9,0) | M9: Loan Amount | N9: 45000000 | O9: =K12 | P9: =N9-O9
A10: Govind Padiya | B10: LNT | C10: Drop Line OD | D10: 2000000 | E10: 67040 | F10: 1720065 | G10: No | H10: =IF(UPPER(G10)="YES",E10,0) | I10: Yes | J10: =IF(UPPER(I10)="YES",E10,0) | K10: =IF(UPPER(I10)="YES",F10,0) | M10: Monthly EMI | N10: 443250 | O10: =J12 | P10: =O10-N10
A11: Govind Padiya (Rohan) | B11: BOI | C11: Education Loan | D11: 2500000 | E11: 25000 | F11: 2660643 | G11: No | H11: =IF(UPPER(G11)="YES",E11,0) | I11: Yes | J11: =IF(UPPER(I11)="YES",E11,0) | K11: =IF(UPPER(I11)="YES",F11,0)
A12: Total | D12: =SUM(D4:D11) | E12: =SUM(E4:E11) | F12: =SUM(F4:F11) | H12: =SUM(H4:H11) | J12: =SUM(J4:J11) | K12: =SUM(K4:K11)
